hmo/HMO-DragAtomdev.py
hmo/HMO-v0.5.1dev.py
hmo/HMO.py
hmo/HMO.spec
hmo/HMO_v00dev.py
hmo/HMO_v01dev.py
hmo/HMO_v02dev.py
hmo/HMO_v03dev.py
hmo/HMO_v04dev.py
hmo/MakeApp
hmo/__init__.py
hmo/makeArchive4Linux.sh
hmo/.ipynb_checkpoints/HMO-checkpoint.py
hmo/.ipynb_checkpoints/HMO_v04dev-checkpoint.py
hmo/DesignOfMOdiagram/1e.png
hmo/DesignOfMOdiagram/1e.svg
hmo/DesignOfMOdiagram/2e.png
hmo/DesignOfMOdiagram/2e.svg
hmo/DesignOfMOdiagram/__init__.py
hmo/DesignOfMOdiagram/energy_level.png
hmo/DesignOfMOdiagram/energy_level.svg
hmo/DesignOfMOdiagram/my_molecule_charges_bonds.png
hmo/Fonts/__init__.py
hmo/Fonts/OpenSans/OFL.txt
"hmo/Fonts/OpenSans/OpenSans-Italic-VariableFont_wdth,wght.ttf"
"hmo/Fonts/OpenSans/OpenSans-VariableFont_wdth,wght.ttf"
hmo/Fonts/OpenSans/README.txt
hmo/Fonts/OpenSans/__init__.py
hmo/Fonts/OpenSans/static/OpenSans-Bold.ttf
hmo/Fonts/OpenSans/static/OpenSans-BoldItalic.ttf
hmo/Fonts/OpenSans/static/OpenSans-ExtraBold.ttf
hmo/Fonts/OpenSans/static/OpenSans-ExtraBoldItalic.ttf
hmo/Fonts/OpenSans/static/OpenSans-Italic.ttf
hmo/Fonts/OpenSans/static/OpenSans-Light.ttf
hmo/Fonts/OpenSans/static/OpenSans-LightItalic.ttf
hmo/Fonts/OpenSans/static/OpenSans-Medium.ttf
hmo/Fonts/OpenSans/static/OpenSans-MediumItalic.ttf
hmo/Fonts/OpenSans/static/OpenSans-Regular.ttf
hmo/Fonts/OpenSans/static/OpenSans-SemiBold.ttf
hmo/Fonts/OpenSans/static/OpenSans-SemiBoldItalic.ttf
hmo/Fonts/OpenSans/static/OpenSans_Condensed-Bold.ttf
hmo/Fonts/OpenSans/static/OpenSans_Condensed-BoldItalic.ttf
hmo/Fonts/OpenSans/static/OpenSans_Condensed-ExtraBold.ttf
hmo/Fonts/OpenSans/static/OpenSans_Condensed-ExtraBoldItalic.ttf
hmo/Fonts/OpenSans/static/OpenSans_Condensed-Italic.ttf
hmo/Fonts/OpenSans/static/OpenSans_Condensed-Light.ttf
hmo/Fonts/OpenSans/static/OpenSans_Condensed-LightItalic.ttf
hmo/Fonts/OpenSans/static/OpenSans_Condensed-Medium.ttf
hmo/Fonts/OpenSans/static/OpenSans_Condensed-MediumItalic.ttf
hmo/Fonts/OpenSans/static/OpenSans_Condensed-Regular.ttf
hmo-0.7.7.dist-info/licenses/LICENSE
hmo-0.7.7.dist-info/METADATA
hmo-0.7.7.dist-info/WHEEL
hmo-0.7.7.dist-info/top_level.txt
hmo-0.7.7.dist-info/RECORD
