Metadata-Version: 2.4
Name: HMO
Version: 0.7.7
Summary: interactive application that allows users to draw the sigma skeleton of conjugated systems, build the corresponding Hückel matrix, calculate π molecular orbitals, and visualize the numerical results as tables and graphics
Author-email: "Romuald POTEAU, LPCNO" <romuald.poteau@utoulouse.fr>
Project-URL: Documentation, https://hmo.readthedocs.io/
Project-URL: Repository, https://github.com/rpoteau/HMO
Project-URL: Changelog, https://github.com/rpoteau/HMO/blob/main/CHANGELOG.md
Requires-Python: >=3.8
License-File: LICENSE
Requires-Dist: numpy
Requires-Dist: pandas
Requires-Dist: matplotlib
Requires-Dist: scipy
Requires-Dist: ipywidgets
Requires-Dist: jupyter
Requires-Dist: Pillow
Requires-Dist: openpyxl
Provides-Extra: docs
Requires-Dist: sphinx; extra == "docs"
Requires-Dist: sphinx_rtd_theme; extra == "docs"
Requires-Dist: myst-parser; extra == "docs"
Requires-Dist: numpydoc; extra == "docs"
Dynamic: license-file
